zind/api/__init__.py
zind/api/core_find.py
zind/api/core_text_find.py
zind/api/file_filter_token.py
zind/api/text_token.py
zind/input/__init__.py
zind/input/loader.py
zind/run/__init__.py
zind/run/runner.py
zind-0.1.3.dist-info/LICENSE
zind-0.1.3.dist-info/METADATA
zind-0.1.3.dist-info/WHEEL
zind-0.1.3.dist-info/entry_points.txt
zind-0.1.3.dist-info/top_level.txt
zind-0.1.3.dist-info/RECORD
